uk_election_timetables/__init__.py
uk_election_timetables/bank-holidays.json
uk_election_timetables/bank_holidays.py
uk_election_timetables/calendars.py
uk_election_timetables/date.py
uk_election_timetables/election.py
uk_election_timetables/election_ids.py
uk_election_timetables/elections/__init__.py
uk_election_timetables/elections/city_of_london_local.py
uk_election_timetables/elections/greater_london_assembly.py
uk_election_timetables/elections/local.py
uk_election_timetables/elections/mayor.py
uk_election_timetables/elections/northern_ireland_assembly.py
uk_election_timetables/elections/police_and_crime_commissioner.py
uk_election_timetables/elections/referendum.py
uk_election_timetables/elections/scottish_parliament.py
uk_election_timetables/elections/senedd_cymru.py
uk_election_timetables/elections/uk_parliament.py
uk_election_timetables-4.3.0.dist-info/licenses/LICENSE.md
uk_election_timetables-4.3.0.dist-info/METADATA
uk_election_timetables-4.3.0.dist-info/WHEEL
uk_election_timetables-4.3.0.dist-info/top_level.txt
uk_election_timetables-4.3.0.dist-info/RECORD
