Metadata-Version: 2.4
Name: uk-election-timetables
Version: 4.3.0
Summary: Derives significant dates for UK elections
Home-page: https://github.com/DemocracyClub/uk-election-timetables
Author: Alex Wilson
Author-email: alex+github@probablyfine.co.uk
License: MIT
Classifier: License :: OSI Approved :: MIT License
Classifier: Topic :: Software Development
Classifier: Topic :: Software Development :: Documentation
License-File: LICENSE.md
Dynamic: author
Dynamic: author-email
Dynamic: classifier
Dynamic: description
Dynamic: description-content-type
Dynamic: home-page
Dynamic: license
Dynamic: license-file
Dynamic: summary
